pysher/__init__.py
pysher/channel.py
pysher/connection.py
pysher/pusher.py
pysher-elytica/__init__.py
pysher-elytica/channel.py
pysher-elytica/connection.py
pysher-elytica/pusher.py
elytica_pysher-1.0.7.dist-info/LICENSE
elytica_pysher-1.0.7.dist-info/METADATA
elytica_pysher-1.0.7.dist-info/WHEEL
elytica_pysher-1.0.7.dist-info/top_level.txt
elytica_pysher-1.0.7.dist-info/RECORD
