Metadata-Version: 2.1
Name: elytica-pysher
Version: 1.0.7
Summary: Pusher websocket client for python, based on Erik Kulyk's PythonPusherClient and Nils Diefenbach Pysher. This package has some fixes to support laravel-websockets(beyondcode) support.
Home-page: https://github.com/baggins800/Pysher
Author: Ruan Luies
Author-email: ruan@elytica.com
License: MIT
Keywords: pusher websocket client
Platform: UNKNOWN
Classifier: Development Status :: 4 - Beta
Classifier: Environment :: Web Environment
Classifier: License :: OSI Approved :: MIT License
Classifier: Programming Language :: Python
Classifier: Programming Language :: Python :: 3.5
Classifier: Programming Language :: Python :: 3.6
Classifier: Programming Language :: Python :: 3.7
Classifier: Topic :: Internet
Classifier: Topic :: Software Development :: Libraries 
Classifier: Topic :: Software Development :: Libraries :: Python Modules
Requires-Dist: websocket-client (!=0.49)
